MuSeqPose/__init__.py
MuSeqPose/config.py
MuSeqPose/pose_kit.py
MuSeqPose/ui_Skeleton.py
MuSeqPose/Resources/AlignmentDialog.ui
MuSeqPose/Resources/AnnotationWidget.ui
MuSeqPose/Resources/CalibrationWidget.ui
MuSeqPose/Resources/HeadingAnalysis.ui
MuSeqPose/Resources/KeyPoint.ui
MuSeqPose/Resources/OperationCard.ui
MuSeqPose/Resources/OptiPosePipeline.ui
MuSeqPose/Resources/PipelineWidget.ui
MuSeqPose/Resources/PlayControl.ui
MuSeqPose/Resources/ProcessorConfigurator.ui
MuSeqPose/Resources/SyncViewPlayer.ui
MuSeqPose/Resources/main.ui
MuSeqPose/player_interface/PlayerInterface.py
MuSeqPose/player_interface/PlotPlayer.py
MuSeqPose/player_interface/VideoPlayer.py
MuSeqPose/utils/FlowLayout.py
MuSeqPose/utils/pipeline_execution_manager.py
MuSeqPose/utils/processor_thread.py
MuSeqPose/utils/session_manager.py
MuSeqPose/utils/ui_generators.py
MuSeqPose/widgets/AlignmentWidget.py
MuSeqPose/widgets/AnnotationWidget.py
MuSeqPose/widgets/CalibrationWidget.py
MuSeqPose/widgets/HeadingAnalysisWidget.py
MuSeqPose/widgets/ImageViewer.py
MuSeqPose/widgets/OperationCardWidget.py
MuSeqPose/widgets/OptiPosePipeline.py
MuSeqPose/widgets/PipelineWidget.py
MuSeqPose/widgets/PlayControlWidget.py
MuSeqPose/widgets/ProcessorCardWidget.py
MuSeqPose/widgets/SyncViewWidget.py
MuSeqPose/widgets/ui_KeyPoint.py
MuSeqPose-0.0.2.1.dist-info/METADATA
MuSeqPose-0.0.2.1.dist-info/WHEEL
MuSeqPose-0.0.2.1.dist-info/entry_points.txt
MuSeqPose-0.0.2.1.dist-info/top_level.txt
MuSeqPose-0.0.2.1.dist-info/RECORD
