Metadata-Version: 2.1
Name: MuSeqPose
Version: 0.0.2.1
Summary: A toolkit to reconstruct,post-process, and analyze 3D Poses
Author-email: Mahir Patel <mahirp@bu.edu>
Classifier: Programming Language :: Python :: 3
Classifier: License :: OSI Approved :: MIT License
Classifier: Operating System :: OS Independent
Requires-Python: <3.11,>=3.10
Requires-Dist: bu-cvkit
Requires-Dist: vispy
